[
    {
        "key": "dbln",
        "value": "%7B%22100089997213872%22%3A%222vPrNmZo%22%2C%2261587040571033%22%3A%225fPqixal%22%2C%2261587635203322%22%3A%22S3fzqHsm%22%7D",
        "domain": "facebook.com",
        "path": "/login/device-based/",
        "hostOnly": false,
        "creation": "2026-02-11T11:21:19.628Z",
        "lastAccessed": "2026-02-11T11:21:19.629Z"
    },
    {
        "key": "datr",
        "value": "szKHaQfP6jXrCko8ZqjdpxHA",
        "domain": "facebook.com",
        "path": "/",
        "hostOnly": false,
        "creation": "2026-02-11T11:21:19.629Z",
        "lastAccessed": "2026-02-11T11:21:19.629Z"
    },
    {
        "key": "sb",
        "value": "J0uHaYpUfkyRZJ6h90jHyCkI",
        "domain": "facebook.com",
        "path": "/",
        "hostOnly": false,
        "creation": "2026-02-11T11:21:19.629Z",
        "lastAccessed": "2026-02-11T11:21:19.629Z"
    },
    {
        "key": "ps_l",
        "value": "1",
        "domain": "facebook.com",
        "path": "/",
        "hostOnly": false,
        "creation": "2026-02-11T11:21:19.629Z",
        "lastAccessed": "2026-02-11T11:21:19.629Z"
    },
    {
        "key": "ps_n",
        "value": "1",
        "domain": "facebook.com",
        "path": "/",
        "hostOnly": false,
        "creation": "2026-02-11T11:21:19.629Z",
        "lastAccessed": "2026-02-11T11:21:19.629Z"
    },
    {
        "key": "locale",
        "value": "en_US",
        "domain": "facebook.com",
        "path": "/",
        "hostOnly": false,
        "creation": "2026-02-11T11:21:19.629Z",
        "lastAccessed": "2026-02-11T11:21:19.629Z"
    },
    {
        "key": "dpr",
        "value": "2.2872583866119385",
        "domain": "facebook.com",
        "path": "/",
        "hostOnly": false,
        "creation": "2026-02-11T11:21:19.629Z",
        "lastAccessed": "2026-02-11T11:21:19.629Z"
    },
    {
        "key": "pas",
        "value": "61587109403745%3A0ubzcI4BSA%2C100069796207006%3AaxZMJl0Ies%2C61587288375563%3ASZabPeR2GM%2C61587040571033%3Arnsb3hVHiP",
        "domain": "facebook.com",
        "path": "/",
        "hostOnly": false,
        "creation": "2026-02-11T11:21:19.629Z",
        "lastAccessed": "2026-02-11T11:21:19.629Z"
    },
    {
        "key": "vpd",
        "value": "v1%3B677x346x2.080371856689453",
        "domain": "facebook.com",
        "path": "/",
        "hostOnly": false,
        "creation": "2026-02-11T11:21:19.629Z",
        "lastAccessed": "2026-02-11T11:21:19.629Z"
    },
    {
        "key": "wl_cbv",
        "value": "v2%3Bclient_version%3A3081%3Btimestamp%3A1770729098",
        "domain": "facebook.com",
        "path": "/",
        "hostOnly": false,
        "creation": "2026-02-11T11:21:19.629Z",
        "lastAccessed": "2026-02-11T11:21:19.629Z"
    },
    {
        "key": "wd",
        "value": "685x1341",
        "domain": "facebook.com",
        "path": "/",
        "hostOnly": false,
        "creation": "2026-02-11T11:21:19.629Z",
        "lastAccessed": "2026-02-11T11:21:19.629Z"
    },
    {
        "key": "c_user",
        "value": "61587635203322",
        "domain": "facebook.com",
        "path": "/",
        "hostOnly": false,
        "creation": "2026-02-11T11:21:19.629Z",
        "lastAccessed": "2026-02-11T11:21:19.629Z"
    },
    {
        "key": "fr",
        "value": "1SuQzE9ycYKSHl2tJ.AWeRu40bEQMgzd4Z4QC-2xPZnx7AnI5yY55g2McCOqcW3lEJNn8.BpjGYv..AAA.0.0.BpjGYv.AWf_rOJxA4f2EIpSvCGBc0pNmL4",
        "domain": "facebook.com",
        "path": "/",
        "hostOnly": false,
        "creation": "2026-02-11T11:21:19.629Z",
        "lastAccessed": "2026-02-11T11:21:19.629Z"
    },
    {
        "key": "xs",
        "value": "6%3AS6Lk68aUA09V6Q%3A2%3A1770807018%3A-1%3A-1%3A%3AAcyV9nrNeCZcq-z6JXoYLf7Oh-KUMjM1Gn5j2iFK6Q",
        "domain": "facebook.com",
        "path": "/",
        "hostOnly": false,
        "creation": "2026-02-11T11:21:19.629Z",
        "lastAccessed": "2026-02-11T11:21:19.629Z"
    }
]
