[
    {
        "key": "dbln",
        "value": "%7B%2261587928367426%22%3A%227BfPje0g%22%2C%2261588008041457%22%3A%222odgSxq9%22%2C%2261585215481090%22%3A%22KkH99D6o%22%7D",
        "domain": "facebook.com",
        "path": "/login/device-based/",
        "hostOnly": false,
        "creation": "2026-03-05T00:05:20.332Z",
        "lastAccessed": "2026-03-05T00:05:20.337Z"
    },
    {
        "key": "sb",
        "value": "yBZ-aYCj89ySh0bYnks8zykJ",
        "domain": "facebook.com",
        "path": "/",
        "hostOnly": false,
        "creation": "2026-03-05T00:05:20.337Z",
        "lastAccessed": "2026-03-05T00:05:20.337Z"
    },
    {
        "key": "ps_l",
        "value": "1",
        "domain": "facebook.com",
        "path": "/",
        "hostOnly": false,
        "creation": "2026-03-05T00:05:20.337Z",
        "lastAccessed": "2026-03-05T00:05:20.337Z"
    },
    {
        "key": "ps_n",
        "value": "1",
        "domain": "facebook.com",
        "path": "/",
        "hostOnly": false,
        "creation": "2026-03-05T00:05:20.337Z",
        "lastAccessed": "2026-03-05T00:05:20.337Z"
    },
    {
        "key": "locale",
        "value": "en_US",
        "domain": "facebook.com",
        "path": "/",
        "hostOnly": false,
        "creation": "2026-03-05T00:05:20.337Z",
        "lastAccessed": "2026-03-05T00:05:20.337Z"
    },
    {
        "key": "dpr",
        "value": "1.7000000476837158",
        "domain": "facebook.com",
        "path": "/",
        "hostOnly": false,
        "creation": "2026-03-05T00:05:20.337Z",
        "lastAccessed": "2026-03-05T00:05:20.337Z"
    },
    {
        "key": "vpd",
        "value": "v1%3B824x424x1.7000000476837158",
        "domain": "facebook.com",
        "path": "/",
        "hostOnly": false,
        "creation": "2026-03-05T00:05:20.337Z",
        "lastAccessed": "2026-03-05T00:05:20.337Z"
    },
    {
        "key": "datr",
        "value": "Dm6oabORh4fgCKJhg5cVX69z",
        "domain": "facebook.com",
        "path": "/",
        "hostOnly": false,
        "creation": "2026-03-05T00:05:20.337Z",
        "lastAccessed": "2026-03-05T00:05:20.337Z"
    },
    {
        "key": "pas",
        "value": "61587285394488%3AsfVAAwVJLt%2C61587040571033%3AjzL8Jcoy0r%2C61587288375563%3ALOB2HqwqQT%2C61588008041457%3AtxMdtcyr5z%2C61587635203322%3AExIkCjuozi%2C61585496604096%3AKW5HNq9exV%2C61585215481090%3AE82cZUcFNW",
        "domain": "facebook.com",
        "path": "/",
        "hostOnly": false,
        "creation": "2026-03-05T00:05:20.337Z",
        "lastAccessed": "2026-03-05T00:05:20.337Z"
    },
    {
        "key": "c_user",
        "value": "61587635203322",
        "domain": "facebook.com",
        "path": "/",
        "hostOnly": false,
        "creation": "2026-03-05T00:05:20.337Z",
        "lastAccessed": "2026-03-05T00:05:20.337Z"
    },
    {
        "key": "xs",
        "value": "49%3AfW_-Mk9dAfJz1w%3A2%3A1772667233%3A-1%3A-1",
        "domain": "facebook.com",
        "path": "/",
        "hostOnly": false,
        "creation": "2026-03-05T00:05:20.337Z",
        "lastAccessed": "2026-03-05T00:05:20.337Z"
    },
    {
        "key": "fr",
        "value": "1TlpYqhwTijQFX22b.AWf2buYmxOL4fv4ZpV0uSvMOH0DZGe3HZeo5KfU0s73gRrkriKA.BpqGph..AAA.0.0.BpqMip.AWdNzFvWCe2ed4lRFy9SNG9EEDM",
        "domain": "facebook.com",
        "path": "/",
        "hostOnly": false,
        "creation": "2026-03-05T00:05:20.337Z",
        "lastAccessed": "2026-03-05T00:05:20.337Z"
    },
    {
        "key": "fbl_st",
        "value": "101416533%3BT%3A29544484",
        "domain": "facebook.com",
        "path": "/",
        "hostOnly": false,
        "creation": "2026-03-05T00:05:20.337Z",
        "lastAccessed": "2026-03-05T00:05:20.337Z"
    },
    {
        "key": "wl_cbv",
        "value": "v2%3Bclient_version%3A3103%3Btimestamp%3A1772669097",
        "domain": "facebook.com",
        "path": "/",
        "hostOnly": false,
        "creation": "2026-03-05T00:05:20.337Z",
        "lastAccessed": "2026-03-05T00:05:20.337Z"
    }
]
