[
    {
        "key": "dbln",
        "value": "%7B%2261587535131985%22%3A%22OjyYnhmT%22%7D",
        "domain": "facebook.com",
        "path": "/login/device-based/",
        "hostOnly": false,
        "creation": "2026-02-03T18:28:35.509Z",
        "lastAccessed": "2026-02-03T18:28:35.509Z"
    },
    {
        "key": "datr",
        "value": "yBZ-abcCaT_TTjyBL62y-h_u",
        "domain": "facebook.com",
        "path": "/",
        "hostOnly": false,
        "creation": "2026-02-03T18:28:35.510Z",
        "lastAccessed": "2026-02-03T18:28:35.510Z"
    },
    {
        "key": "sb",
        "value": "yBZ-aYCj89ySh0bYnks8zykJ",
        "domain": "facebook.com",
        "path": "/",
        "hostOnly": false,
        "creation": "2026-02-03T18:28:35.510Z",
        "lastAccessed": "2026-02-03T18:28:35.510Z"
    },
    {
        "key": "ps_l",
        "value": "1",
        "domain": "facebook.com",
        "path": "/",
        "hostOnly": false,
        "creation": "2026-02-03T18:28:35.510Z",
        "lastAccessed": "2026-02-03T18:28:35.510Z"
    },
    {
        "key": "ps_n",
        "value": "1",
        "domain": "facebook.com",
        "path": "/",
        "hostOnly": false,
        "creation": "2026-02-03T18:28:35.510Z",
        "lastAccessed": "2026-02-03T18:28:35.510Z"
    },
    {
        "key": "dpr",
        "value": "1.4375",
        "domain": "facebook.com",
        "path": "/",
        "hostOnly": false,
        "creation": "2026-02-03T18:28:35.510Z",
        "lastAccessed": "2026-02-03T18:28:35.510Z"
    },
    {
        "key": "pas",
        "value": "61587285394488%3AsfVAAwVJLt",
        "domain": "facebook.com",
        "path": "/",
        "hostOnly": false,
        "creation": "2026-02-03T18:28:35.510Z",
        "lastAccessed": "2026-02-03T18:28:35.510Z"
    },
    {
        "key": "locale",
        "value": "en_US",
        "domain": "facebook.com",
        "path": "/",
        "hostOnly": false,
        "creation": "2026-02-03T18:28:35.510Z",
        "lastAccessed": "2026-02-03T18:28:35.510Z"
    },
    {
        "key": "vpd",
        "value": "v1%3B988x501x1.4375",
        "domain": "facebook.com",
        "path": "/",
        "hostOnly": false,
        "creation": "2026-02-03T18:28:35.510Z",
        "lastAccessed": "2026-02-03T18:28:35.510Z"
    },
    {
        "key": "wl_cbv",
        "value": "v2%3Bclient_version%3A3070%3Btimestamp%3A1770132529",
        "domain": "facebook.com",
        "path": "/",
        "hostOnly": false,
        "creation": "2026-02-03T18:28:35.510Z",
        "lastAccessed": "2026-02-03T18:28:35.510Z"
    },
    {
        "key": "wd",
        "value": "979x1930",
        "domain": "facebook.com",
        "path": "/",
        "hostOnly": false,
        "creation": "2026-02-03T18:28:35.510Z",
        "lastAccessed": "2026-02-03T18:28:35.510Z"
    },
    {
        "key": "c_user",
        "value": "61587285394488",
        "domain": "facebook.com",
        "path": "/",
        "hostOnly": false,
        "creation": "2026-02-03T18:28:35.510Z",
        "lastAccessed": "2026-02-03T18:28:35.510Z"
    },
    {
        "key": "fr",
        "value": "1x11Ss122mdFMH90X.AWeId5FL8ATE4CYWVvmN7rqP_tMcxsh7mO8u8cMYIMb1-hFztTg.Bpgj5B..AAA.0.0.Bpgj5B.AWdbKWI92CTGwtNPZ9-grqlwq2U",
        "domain": "facebook.com",
        "path": "/",
        "hostOnly": false,
        "creation": "2026-02-03T18:28:35.510Z",
        "lastAccessed": "2026-02-03T18:28:35.510Z"
    },
    {
        "key": "xs",
        "value": "29%3AWFkUF-YSN0_IiA%3A2%3A1770143290%3A-1%3A-1%3A%3AAczeGQlU0BFNORkhBUgeN5MXe4G4wAaKRv-HkOfXLA",
        "domain": "facebook.com",
        "path": "/",
        "hostOnly": false,
        "creation": "2026-02-03T18:28:35.510Z",
        "lastAccessed": "2026-02-03T18:28:35.510Z"
    },
    {
        "key": "presence",
        "value": "C%7B%22t3%22%3A%5B%5D%2C%22utc3%22%3A1770143299625%2C%22v%22%3A1%7D",
        "domain": "facebook.com",
        "path": "/",
        "hostOnly": false,
        "creation": "2026-02-03T18:28:35.510Z",
        "lastAccessed": "2026-02-03T18:28:35.510Z"
    }
]
