[
    {
        "key": "dbln",
        "value": "%7B%2261587535131985%22%3A%22QM3bRLgU%22%7D",
        "domain": "facebook.com",
        "path": "/login/device-based/",
        "hostOnly": false,
        "creation": "2026-02-05T13:35:23.964Z",
        "lastAccessed": "2026-02-05T13:35:23.964Z"
    },
    {
        "key": "datr",
        "value": "uwx-abT5YsUaHfEpz3B0BmTX",
        "domain": "facebook.com",
        "path": "/",
        "hostOnly": false,
        "creation": "2026-02-05T13:35:23.964Z",
        "lastAccessed": "2026-02-05T13:35:23.964Z"
    },
    {
        "key": "sb",
        "value": "uwx-aRnv-ZKm5knaDOXuAwDW",
        "domain": "facebook.com",
        "path": "/",
        "hostOnly": false,
        "creation": "2026-02-05T13:35:23.964Z",
        "lastAccessed": "2026-02-05T13:35:23.964Z"
    },
    {
        "key": "ps_l",
        "value": "1",
        "domain": "facebook.com",
        "path": "/",
        "hostOnly": false,
        "creation": "2026-02-05T13:35:23.964Z",
        "lastAccessed": "2026-02-05T13:35:23.964Z"
    },
    {
        "key": "ps_n",
        "value": "1",
        "domain": "facebook.com",
        "path": "/",
        "hostOnly": false,
        "creation": "2026-02-05T13:35:23.964Z",
        "lastAccessed": "2026-02-05T13:35:23.964Z"
    },
    {
        "key": "locale",
        "value": "en_US",
        "domain": "facebook.com",
        "path": "/",
        "hostOnly": false,
        "creation": "2026-02-05T13:35:23.964Z",
        "lastAccessed": "2026-02-05T13:35:23.964Z"
    },
    {
        "key": "pas",
        "value": "61586868105004%3A9SH8yxpjPU",
        "domain": "facebook.com",
        "path": "/",
        "hostOnly": false,
        "creation": "2026-02-05T13:35:23.964Z",
        "lastAccessed": "2026-02-05T13:35:23.964Z"
    },
    {
        "key": "vpd",
        "value": "v1%3B760x386x1.869084119796753",
        "domain": "facebook.com",
        "path": "/",
        "hostOnly": false,
        "creation": "2026-02-05T13:35:23.964Z",
        "lastAccessed": "2026-02-05T13:35:23.964Z"
    },
    {
        "key": "wl_cbv",
        "value": "v2%3Bclient_version%3A3070%3Btimestamp%3A1769977802",
        "domain": "facebook.com",
        "path": "/",
        "hostOnly": false,
        "creation": "2026-02-05T13:35:23.964Z",
        "lastAccessed": "2026-02-05T13:35:23.964Z"
    },
    {
        "key": "dpr",
        "value": "1.9388089179992676",
        "domain": "facebook.com",
        "path": "/",
        "hostOnly": false,
        "creation": "2026-02-05T13:35:23.964Z",
        "lastAccessed": "2026-02-05T13:35:23.964Z"
    },
    {
        "key": "wd",
        "value": "685x1359",
        "domain": "facebook.com",
        "path": "/",
        "hostOnly": false,
        "creation": "2026-02-05T13:35:23.964Z",
        "lastAccessed": "2026-02-05T13:35:23.964Z"
    },
    {
        "key": "c_user",
        "value": "61587535131985",
        "domain": "facebook.com",
        "path": "/",
        "hostOnly": false,
        "creation": "2026-02-05T13:35:23.964Z",
        "lastAccessed": "2026-02-05T13:35:23.964Z"
    },
    {
        "key": "xs",
        "value": "24%3ACPO5qHpUtU8XPw%3A2%3A1770298519%3A-1%3A-1",
        "domain": "facebook.com",
        "path": "/",
        "hostOnly": false,
        "creation": "2026-02-05T13:35:23.964Z",
        "lastAccessed": "2026-02-05T13:35:23.964Z"
    },
    {
        "key": "fr",
        "value": "1AkOnSXxDDHWcNtFB.AWfONY9vBWv_nyHgzEnbRn9HA7_eJmxof-JsF8D5md1_pGxfWn0.BphGnQ..AAA.0.0.BphJyY.AWdX2JSTF2RqXZexkO2h1mC20F0",
        "domain": "facebook.com",
        "path": "/",
        "hostOnly": false,
        "creation": "2026-02-05T13:35:23.964Z",
        "lastAccessed": "2026-02-05T13:35:23.964Z"
    }
]
